pyci/__init__.py
pyci/api/__init__.py
pyci/api/exceptions.py
pyci/api/logger.py
pyci/api/runner.py
pyci/api/utils.py
pyci/api/ci/__init__.py
pyci/api/ci/ci.py
pyci/api/model/__init__.py
pyci/api/model/model.py
pyci/api/package/__init__.py
pyci/api/package/packager.py
pyci/api/publish/__init__.py
pyci/api/publish/pypi.py
pyci/api/scm/__init__.py
pyci/api/scm/gh.py
pyci/resources/__init__.py
pyci/resources/changelog.jinja
pyci/resources/pyci.ascii
pyci/resources/virtualenv.py
pyci/resources/virtualenv_support/__init__.py
pyci/resources/virtualenv_support/pip-19.1.1-py2.py3-none-any.whl
pyci/resources/virtualenv_support/setuptools-41.0.1-py2.py3-none-any.whl
pyci/resources/windows_support/__init__.py
pyci/resources/windows_support/installer.nsi.jinja
pyci/resources/windows_support/nsis-3.04.zip
pyci/resources/windows_support/path.nsh
pyci/shell/__init__.py
pyci/shell/causes.py
pyci/shell/context.py
pyci/shell/exceptions.py
pyci/shell/help.py
pyci/shell/logger.py
pyci/shell/main.py
pyci/shell/secrets.py
pyci/shell/solutions.py
pyci/shell/commands/__init__.py
pyci/shell/commands/release.py
pyci/shell/subcommands/__init__.py
pyci/shell/subcommands/ci.py
pyci/shell/subcommands/github.py
pyci/shell/subcommands/pack.py
pyci/shell/subcommands/pypi.py
py_ci-0.8.3.dist-info/LICENSE
py_ci-0.8.3.dist-info/METADATA
py_ci-0.8.3.dist-info/WHEEL
py_ci-0.8.3.dist-info/entry_points.txt
py_ci-0.8.3.dist-info/top_level.txt
py_ci-0.8.3.dist-info/RECORD
