Metadata-Version: 2.1
Name: py-ci
Version: 0.8.3
Summary: CI toolchain for Python projects
Home-page: https://github.com/iliapolo/pyci/
Author: Eli Polonsky
Author-email: eli.polonsky@gmail.com
License: LICENSE
Platform: UNKNOWN
Classifier: Programming Language :: Python
Classifier: Programming Language :: Python :: 2.7
Classifier: Programming Language :: Python :: 3.6
Classifier: Natural Language :: English
Classifier: Environment :: Console
Classifier: Intended Audience :: Developers
Classifier: Intended Audience :: Information Technology
Classifier: Intended Audience :: System Administrators
Classifier: License :: OSI Approved :: Apache Software License
Classifier: Operating System :: POSIX :: Linux
Classifier: Operating System :: Microsoft
Classifier: Topic :: Software Development :: Libraries :: Python Modules
Requires-Dist: click (==7.0)
Requires-Dist: semver (==2.8.0)
Requires-Dist: PyGithub (==1.40)
Requires-Dist: requests (==2.22.0)
Requires-Dist: jinja2 (==2.10.1)
Requires-Dist: boltons (==18.0.0)
Requires-Dist: twine (==1.11.0)
Requires-Dist: six (==1.11.0)
Requires-Dist: colorama (==0.3.9)
Requires-Dist: wheel (==0.33.4)
Requires-Dist: packaging (==19.0)
